Workbook

Sheet Декомпозиция
A1: SyncVoice™ Platform — Декомпозиция и оценка по специалистам
A2: Ставка: 3 000 руб./ч (все специалисты) | Разработка с нуля | On-premise, GPU | Буфер 15% отдельной строкой | M2: Ставка: | N2: 3000
A3: № | B3: Функция / Блок | C3: Приор. | D3: Аналит.,ч | E3: Разраб. BE,ч | F3: Разраб. FE,ч | G3: QA,ч | H3: PM,ч | I3: DevOps,ч | J3: Итого,ч | K3: Стоимость, руб. | L3: Примечание
B4: АРХИТЕКТУРА И ПРОЕКТИРОВАНИЕ
A5: 1.1 | B5: Анализ требований ТЗ, проектирование архитектуры | C5: M | D5: 20 | E5: 16 | H5: 12 | J5: =SUM(D5:I5) | K5: =J5*$N$2 | L5: Модульная архитектура: ASR→NMT→TTS pipeline
A6: 1.2 | B6: Проектирование API-контрактов (streaming + REST) | C6: M | D6: 16 | E6: 24 | F6: 8 | H6: 4 | J6: =SUM(D6:I6) | K6: =J6*$N$2 | L6: WebSocket/WebRTC протоколы, REST для AdminPortal
A7: 1.3 | B7: Проектирование БД (глоссарии, сессии, логи, аудит) | C7: M | D7: 12 | E7: 16 | H7: 4 | J7: =SUM(D7:I7) | K7: =J7*$N$2 | L7: PostgreSQL: glossary, sessions, audit_log, users
A8: 1.4 | B8: Настройка проекта (CI/CD, Docker dev, lint) | C8: M | E8: 8 | F8: 8 | H8: 4 | I8: 16 | J8: =SUM(D8:I8) | K8: =J8*$N$2 | L8: Docker Compose для dev, pre-commit hooks
B9: VOICECORE™ ASR ENGINE
A10: 2.1 | B10: Интеграция streaming ASR (Whisper / faster-whisper) | C10: M | D10: 8 | E10: 60 | G10: 16 | H10: 4 | I10: 8 | J10: =SUM(D10:I10) | K10: =J10*$N$2 | L10: Real-time inference, GPU оптимизация
A11: 2.2 | B11: SmartPause™ — детекция пауз и сегментация речи | C11: M | D11: 8 | E11: 40 | G11: 16 | H11: 4 | I11: 4 | J11: =SUM(D11:I11) | K11: =J11*$N$2 | L11: VAD + пороговая логика, буферизация
A12: 2.3 | B12: Speaker adaptation / fine-tune (5 спикеров) | C12: S | D12: 8 | E12: 48 | G12: 24 | H12: 4 | I12: 8 | J12: =SUM(D12:I12) | K12: =J12*$N$2 | L12: ⚠ Кол-во спикеров не определено, буфер на 5
A13: 2.4 | B13: Языковые модели EN, RU, HI | C13: M | D13: 4 | E13: 24 | G13: 16 | H13: 4 | I13: 4 | J13: =SUM(D13:I13) | K13: =J13*$N$2 | L13: Загрузка, тест, калибровка по каждому языку
B14: NEUROTRANSLATE™ NMT MODULE
A15: 3.1 | B15: Интеграция SeamlessM4T / NLLB | C15: M | D15: 16 | E15: 40 | H15: 8 | I15: 8 | J15: =SUM(D15:I15) | K15: =J15*$N$2 | L15: Encoder-decoder, выбор модели, бенчмарк
A16: 3.2 | B16: Streaming mode с partial results | C16: M | D16: 8 | E16: 48 | G16: 24 | H16: 4 | I16: 8 | J16: =SUM(D16:I16) | K16: =J16*$N$2 | L16: Инкрементальный перевод для <2 сек latency
A17: 3.3 | B17: Интеграция с GlossaryAI™ — приоритет терминов | C17: M | D17: 12 | E17: 60 | G17: 24 | H17: 4 | I17: 4 | J17: =SUM(D17:I17) | K17: =J17*$N$2 | L17: Constrained decoding / post-processing терминов
A18: 3.4 | B18: Контекстное окно 512 токенов | C18: M | D18: 4 | E18: 32 | G18: 16 | H18: 4 | I18: 4 | J18: =SUM(D18:I18) | K18: =J18*$N$2 | L18: Скользящее окно, кеширование контекста
A19: 3.5 | B19: 200+ языковых пар (zero-shot для редких) | C19: S | D19: 8 | E19: 40 | G19: 32 | H19: 4 | I19: 4 | J19: =SUM(D19:I19) | K19: =J19*$N$2 | L19: ⚠ Качество неравномерное, гарантия на EN↔RU/HI
B20: VOICESYNTH™ TTS ENGINE
A21: 4.1 | B21: Интеграция нейросетевого TTS (Coqui/XTTS) | C21: M | D21: 12 | E21: 40 | H21: 8 | I21: 8 | J21: =SUM(D21:I21) | K21: =J21*$N$2 | L21: Выбор модели, бенчмарк MOS >4.0
A22: 4.2 | B22: Streaming mode (~600ms latency) | C22: M | D22: 4 | E22: 48 | G22: 24 | H22: 4 | I22: 8 | J22: =SUM(D22:I22) | K22: =J22*$N$2 | L22: Chunk-based генерация, буферизация
A23: 4.3 | B23: Подбор и настройка голосов (MOS >4.0) | C23: M | D23: 8 | E23: 60 | G23: 32 | H23: 4 | I23: 4 | J23: =SUM(D23:I23) | K23: =J23*$N$2 | L23: A/B тестирование голосов, субъективная оценка
A24: 4.4 | B24: Premium голоса — расширенный пакет | C24: C | D24: 4 | E24: 24 | G24: 16 | H24: 4 | I24: 4 | J24: =SUM(D24:I24) | K24: =J24*$N$2 | L24: Опциональный модуль
B25: STREAMORCHESTRATOR™
A26: 5.1 | B26: WebSocket / WebRTC оркестрация потоков | C26: M | D26: 12 | E26: 80 | G26: 32 | H26: 8 | I26: 16 | J26: =SUM(D26:I26) | K26: =J26*$N$2 | L26: Основной pipeline: аудиовход→ASR→NMT→TTS→аудиовыход
A27: 5.2 | B27: Pipeline управление (ASR→NMT→TTS chain) | C27: M | D27: 8 | E27: 60 | G27: 24 | H27: 4 | I27: 8 | J27: =SUM(D27:I27) | K27: =J27*$N$2 | L27: Очередь, backpressure, graceful degradation
A28: 5.3 | B28: Параллельная обработка 2 аудиопотоков | C28: M | D28: 4 | E28: 40 | G28: 24 | H28: 4 | I28: 8 | J28: =SUM(D28:I28) | K28: =J28*$N$2 | L28: Thread/process pool, распределение GPU
A29: 5.4 | B29: Мониторинг latency, автоматический fallback | C29: S | D29: 4 | E29: 32 | G29: 16 | H29: 4 | I29: 8 | J29: =SUM(D29:I29) | K29: =J29*$N$2 | L29: Prometheus метрики, алерты >2 сек
B30: GLOSSARYAI™ (>2000 ЗАПИСЕЙ)
A31: 6.1 | B31: CRUD глоссариев — импорт Excel, CSV, TBX | C31: M | D31: 12 | E31: 32 | F31: 16 | G31: 20 | H31: 4 | I31: 4 | J31: =SUM(D31:I31) | K31: =J31*$N$2 | L31: Парсинг, валидация, дедупликация
A32: 6.2 | B32: Извлечение терминов из PDF (NER/regex) | C32: S | D32: 8 | E32: 60 | G32: 24 | H32: 4 | I32: 4 | J32: =SUM(D32:I32) | K32: =J32*$N$2 | L32: PyMuPDF + SpaCy NER для хим. соединений
A33: 6.3 | B33: Фонетические транскрипции для TTS | C33: M | D33: 4 | E33: 32 | G33: 16 | H33: 4 | J33: =SUM(D33:I33) | K33: =J33*$N$2 | L33: IPA генерация, интеграция с VoiceSynth
A34: 6.4 | B34: Версионирование, правила «не переводить» | C34: M | D34: 8 | E34: 32 | F34: 8 | G34: 16 | H34: 4 | I34: 4 | J34: =SUM(D34:I34) | K34: =J34*$N$2 | L34: Git-like версионирование, whitelist кодов
A35: 6.5 | B35: Валидация глоссария >2000 записей | C35: M | D35: 8 | G35: 32 | H35: 4 | J35: =SUM(D35:I35) | K35: =J35*$N$2 | L35: ⚠ Большой объём, ручная + автоматическая проверка
B36: SYNCBRIDGE™ (ИНТЕГРАЦИЯ ВКС)
A37: 7.1 | B37: Zoom Language Interpretation API | C37: M | D37: 12 | E37: 80 | G37: 40 | H37: 8 | I37: 12 | J37: =SUM(D37:I37) | K37: =J37*$N$2 | L37: ⚠ API может иметь ограничения, буфер на workaround
A38: 7.2 | B38: Microsoft Teams Audio API | C38: M | D38: 12 | E38: 80 | G38: 40 | H38: 8 | I38: 12 | J38: =SUM(D38:I38) | K38: =J38*$N$2 | L38: ⚠ Аналогично, Teams API менее зрелый
A39: 7.3 | B39: Управление аудиоканалами + маршрутизация | C39: M | D39: 8 | E39: 40 | G39: 24 | H39: 4 | I39: 8 | J39: =SUM(D39:I39) | K39: =J39*$N$2 | L39: Микширование, громкость оригинала, переключение
B40: ADMINPORTAL™ (ВЕБ-ИНТЕРФЕЙС)
A41: 8.1 | B41: Dashboard мониторинга в реальном времени | C41: M | D41: 8 | E41: 16 | F41: 48 | G41: 24 | H41: 4 | I41: 4 | J41: =SUM(D41:I41) | K41: =J41*$N$2 | L41: WebSocket обновления, графики latency/нагрузки
A42: 8.2 | B42: Управление активными сессиями перевода | C42: M | D42: 8 | E42: 16 | F42: 40 | G42: 20 | H42: 4 | I42: 4 | J42: =SUM(D42:I42) | K42: =J42*$N$2 | L42: Старт/стоп, просмотр статуса, ручное переключение
A43: 8.3 | B43: Управление глоссариями (UI) | C43: M | D43: 8 | E43: 8 | F43: 40 | G43: 20 | H43: 4 | I43: 4 | J43: =SUM(D43:I43) | K43: =J43*$N$2 | L43: Редактирование, импорт, предпросмотр
A44: 8.4 | B44: Логи, статистика использования | C44: S | D44: 4 | E44: 12 | F44: 24 | G44: 16 | H44: 4 | I44: 4 | J44: =SUM(D44:I44) | K44: =J44*$N$2 | L44: Фильтрация, экспорт, графики за период
A45: 8.5 | B45: Пользователи, роли, LDAP/AD + MFA | C45: M | D45: 12 | E45: 24 | F45: 40 | G45: 24 | H45: 4 | I45: 12 | J45: =SUM(D45:I45) | K45: =J45*$N$2 | L45: ⚠ Схема AD неизвестна, буфер
B46: БЕЗОПАСНОСТЬ И ИНФРАСТРУКТУРА
A47: 9.1 | B47: TLS 1.3 + AES-256 шифрование | C47: M | D47: 4 | E47: 40 | G47: 24 | H47: 4 | I47: 16 | J47: =SUM(D47:I47) | K47: =J47*$N$2 | L47: Шифрование данных at rest + in transit
A48: 9.2 | B48: LDAP/AD бэкенд-интеграция + MFA | C48: M | D48: 8 | E48: 48 | G48: 24 | H48: 4 | I48: 16 | J48: =SUM(D48:I48) | K48: =J48*$N$2 | L48: ⚠ Схема AD неизвестна
A49: 9.3 | B49: Аудит-логирование для compliance | C49: M | D49: 8 | E49: 24 | G49: 16 | H49: 4 | I49: 16 | J49: =SUM(D49:I49) | K49: =J49*$N$2 | L49: Полный audit trail: кто, что, когда
A50: 9.4 | B50: Docker / on-premise деплоймент (GPU) | C50: M | D50: 8 | E50: 48 | G50: 24 | H50: 8 | I50: 48 | J50: =SUM(D50:I50) | K50: =J50*$N$2 | L50: Docker Compose + GPU passthrough, HA опционально
A51: 9.5 | B51: HIPAA — полная документация, подготовка к аудиту | C51: M | D51: 32 | G51: 16 | H51: 16 | J51: =SUM(D51:I51) | K51: =J51*$N$2 | L51: ⚠ Аудитор = отд. бюджет ~$5-20k
A52: 9.6 | B52: GDPR + FDA 21 CFR Part 11 compliance | C52: S | D52: 16 | G52: 12 | H52: 12 | J52: =SUM(D52:I52) | K52: =J52*$N$2 | L52: Документация, проверка соответствия
B53: ТЕСТИРОВАНИЕ (СКВОЗНОЕ)
A54: 10.1 | B54: Функциональное тестирование всех модулей | C54: M | D54: 8 | G54: 80 | H54: 8 | J54: =SUM(D54:I54) | K54: =J54*$N$2 | L54: По каждому модулю: ASR/NMT/TTS/Glossary/Admin
A55: 10.2 | B55: Интеграционное E2E тестирование | C55: M | D55: 4 | E55: 8 | F55: 8 | G55: 48 | H55: 4 | I55: 8 | J55: =SUM(D55:I55) | K55: =J55*$N$2 | L55: Полный pipeline + ВКС + AdminPortal
A56: 10.3 | B56: Нагрузочное тестирование (2 потока, <2 сек) | C56: M | D56: 4 | E56: 8 | G56: 48 | H56: 4 | I56: 16 | J56: =SUM(D56:I56) | K56: =J56*$N$2 | L56: k6/Locust, мониторинг GPU, bottleneck анализ
A57: 10.4 | B57: UAT / приёмочные тесты с заказчиком | C57: M | D57: 4 | E57: 8 | G57: 40 | H57: 8 | I57: 4 | J57: =SUM(D57:I57) | K57: =J57*$N$2 | L57: Реальные спикеры, реальный контент
B58: ДОКУМЕНТАЦИЯ И ОБУЧЕНИЕ
A59: 11.1 | B59: Техническая документация (архитектура, API, deploy) | C59: M | D59: 16 | E59: 8 | F59: 4 | H59: 8 | I59: 4 | J59: =SUM(D59:I59) | K59: =J59*$N$2 | L59: Swagger, README, runbook, архитектурные диаграммы
A60: 11.2 | B60: Пользовательская документация | C60: M | D60: 16 | E60: 4 | H60: 8 | J60: =SUM(D60:I60) | K60: =J60*$N$2 | L60: Руководство оператора + руководство участника
A61: 11.3 | B61: Обучение операторов AdminPortal™ | C61: M | D61: 4 | H61: 12 | J61: =SUM(D61:I61) | K61: =J61*$N$2 | L61: 2 сессии × 2ч + материалы
A62: 11.4 | B62: Обучение участников конференций | C62: S | H62: 12 | J62: =SUM(D62:I62) | K62: =J62*$N$2 | L62: Краткая инструкция + демо-сессия
B63: ЗАПУСК И СОПРОВОЖДЕНИЕ
A64: 12.1 | B64: Опытная эксплуатация — пилотный телемост | C64: M | D64: 8 | E64: 16 | G64: 32 | H64: 20 | I64: 16 | J64: =SUM(D64:I64) | K64: =J64*$N$2 | L64: Реальная конференция EN↔RU, EN↔HI
A65: 12.2 | B65: Устранение замечаний по итогам пилота | C65: M | E65: 24 | F65: 8 | G65: 16 | H65: 12 | I65: 8 | J65: =SUM(D65:I65) | K65: =J65*$N$2 | L65: Баги, UX, точность, latency
A66: 12.3 | B66: Финальный запуск + передача заказчику | C66: M | H66: 12 | I66: 16 | J66: =SUM(D66:I66) | K66: =J66*$N$2 | L66: Акт приёмки, передача документации
B67: ИТОГО (базовая оценка) | D67: =SUM(D4:D66) | E67: =SUM(E4:E66) | F67: =SUM(F4:F66) | G67: =SUM(G4:G66) | H67: =SUM(H4:H66) | I67: =SUM(I4:I66) | J67: =SUM(J4:J66) | K67: =J67*$N$2
B68: Буфер / Contingency (15%) | J68: =ROUND(J67*0.15,0) | K68: =J68*$N$2 | L68: Риски: LDAP, спикеры, Zoom/Teams API
B69: ИТОГО С БУФЕРОМ | J69: =J67+J68 | K69: =J69*$N$2

Sheet Сводка
A1: Сводная таблица по специалистам — SyncVoice™ Platform
A2: Специалист | B2: Часов | C2: Ставка руб./ч | D2: Стоимость, руб.
A3: Аналитик | B3: ='Декомпозиция'!D67 | C3: ='Декомпозиция'!$N$2 | D3: =B3*C3
A4: Разработчик Back-End | B4: ='Декомпозиция'!E67 | C4: ='Декомпозиция'!$N$2 | D4: =B4*C4
A5: Разработчик Front-End | B5: ='Декомпозиция'!F67 | C5: ='Декомпозиция'!$N$2 | D5: =B5*C5
A6: Тестировщик (QA) | B6: ='Декомпозиция'!G67 | C6: ='Декомпозиция'!$N$2 | D6: =B6*C6
A7: Руководитель проекта | B7: ='Декомпозиция'!H67 | C7: ='Декомпозиция'!$N$2 | D7: =B7*C7
A8: DevOps-инженер | B8: ='Декомпозиция'!I67 | C8: ='Декомпозиция'!$N$2 | D8: =B8*C8
A9: Базовая оценка | B9: =SUM(B3:B8) | C9: ='Декомпозиция'!$N$2 | D9: =B9*C9
A10: Буфер 15% | B10: =ROUND(B9*0.15,0) | C10: ='Декомпозиция'!$N$2 | D10: =B10*C10
A11: ИТОГО | B11: =B9+B10 | C11: ='Декомпозиция'!$N$2 | D11: =B11*C11
A13: ⚠️ HIPAA: стоимость внешнего аудитора (~$5–20k) НЕ включена — требует отдельного бюджета.
A14: ⚠️ GPU-оборудование для on-premise (~1–2 млн ₽) — отдельная статья расходов заказчика.
A15: 📅 Рекомендуемые сроки: 6–8 месяцев при команде 3–4 BE + ML-инженер + FE + QA + DevOps.
A16: ⚠️ Качество перевода гарантируется для EN↔RU и EN↔HI. Остальные пары — best effort.
